dtools/datastructures/__init__.py
dtools/datastructures/nodes.py
dtools/datastructures/py.typed
dtools/datastructures/queues.py
dtools/datastructures/tuples.py
dtools/datastructures/splitends/__init__.py
dtools/datastructures/splitends/py.typed
dtools/datastructures/splitends/se.py
dtools_datastructures-0.25.2.dist-info/licenses/LICENSE
dtools_datastructures-0.25.2.dist-info/WHEEL
dtools_datastructures-0.25.2.dist-info/METADATA
dtools_datastructures-0.25.2.dist-info/RECORD
