Metadata-Version: 2.4
Name: dtools.datastructures
Version: 0.25.2
Summary: ### Developer Tools - data structures for algorithms **DEPRICATED**
Keywords: datastructures,data structures,fifo,lifo,stack,queue,SplitEnd
Author-email: "Geoffrey R. Scheller" <geoffrey@scheller.com>
Requires-Python: >=3.12
Classifier: Development Status :: 7 - Inactive
Classifier: Framework :: Pytest
Classifier: Intended Audience :: Developers
Classifier: License :: OSI Approved :: Apache Software License
Classifier: Operating System :: OS Independent
Classifier: Programming Language :: Python :: 3.13
Classifier: Typing :: Typed
License-File: LICENSE
Requires-Dist: dtools.circular-array >= 3.9.0, < 3.10
Requires-Dist: dtools.fp >= 1.4.0, < 1.5
Requires-Dist: pytest >=8.3.2 ; extra == "test"
Project-URL: Changelog, https://github.com/grscheller/dtools-datastructures/blob/main/CHANGELOG.md
Project-URL: Documentation, https://grscheller.github.io/dtools-docs/datastructures
Project-URL: Source, https://github.com/grscheller/dtools-datastructures
Provides-Extra: test
